Workbook

Sheet Dashboard
A1: ACCOUNT DASHBOARD
A3: Starting Balance ($) | B3: 5000
A4: Fixed SL (pips) | B4: 12
A5: Default Risk % (editable) | B5: 0.005
A7: Phase1 Target (10%) | B7: =B3*0.1 -> 500
A8: Phase2 Target (5%) | B8: =B3*0.05 -> 250
A10: Daily Drawdown Limit (5%) | B10: =B3*0.05 -> 250
A11: Overall Drawdown Limit (10%) | B11: =B3*0.1 -> 500

Sheet Trade_Journal
A1: Date | B1: Session (IST) | C1: Pair | D1: Setup Type | E1: Direction | F1: Entry Price | G1: Stop Loss Price | H1: Take Profit Price | I1: Stop Loss (pips) | J1: Take Profit (pips) | K1: Lot Size | L1: Risk $ | M1: Reward $ | N1: Result $ | O1: Outcome | P1: Rule Followed? | Q1: Equity After Trade | R1: Notes
A2: ⚠️ DO NOT EDIT COLORED COLUMNS | B2: London | C2: XAUUSD | D2: Breakout retest | E2: Buy | F2: 4383 | G2: 4371 | H2: 4388 | I2: 12 | J2: 5 | K2: 0.02 | L2: =K2*100*I2 -> 24 | M2: =K2*100*J2 -> 10 | N2: =IF(O2="Win",M2,IF(O2="Loss",-L2,"")) -> 10 | O2: Win | P2: Yes | Q2: =IF(SUM(N$2:N2)="",Dashboard!B3,Dashboard!B3+SUM(N$2:N2)) -> 5010
A3: 2025-12-03 | B3: NY | C3: XAUUSD | D3: Liquidity sweep | E3: Sell | F3: 4390 | G3: 4402 | H3: 4385 | I3: 12 | J3: 5 | K3: 0.04 | L3: =K3*100*I3 -> 48 | M3: =K3*100*J3 -> 20 | N3: =IF(O3="Win",M3,IF(O3="Loss",-L3,"")) -> -48 | O3: Loss | P3: No | Q3: =IF(SUM(N$2:N3)="",Dashboard!B3,Dashboard!B3+SUM(N$2:N3)) -> 4962
A4: 2025-12-10 | B4: London | C4: XAUUSD | D4: Rejection wick | E4: Buy | F4: 4360 | G4: 4348 | H4: 4365 | I4: 12 | J4: 5 | K4: 0.02 | L4: =K4*100*I4 -> 24 | M4: =K4*100*J4 -> 10 | N4: =IF(O4="Win",M4,IF(O4="Loss",-L4,"")) -> 10 | O4: Win | P4: Yes | Q4: =IF(SUM(N$2:N4)="",Dashboard!B3,Dashboard!B3+SUM(N$2:N4)) -> 4972
L5: =K5*100*I5 -> 0 | M5: =K5*100*J5 -> 0 | N5: =IF(O5="Win",M5,IF(O5="Loss",-L5,"")) | Q5: =IF(SUM(N$2:N5)="",Dashboard!B3,Dashboard!B3+SUM(N$2:N5)) -> 4972
L6: =K6*100*I6 -> 0 | M6: =K6*100*J6 -> 0 | N6: =IF(O6="Win",M6,IF(O6="Loss",-L6,"")) | Q6: =IF(SUM(N$2:N6)="",Dashboard!B3,Dashboard!B3+SUM(N$2:N6)) -> 4972
L7: =K7*100*I7 -> 0 | M7: =K7*100*J7 -> 0 | N7: =IF(O7="Win",M7,IF(O7="Loss",-L7,"")) | Q7: =IF(SUM(N$2:N7)="",Dashboard!B3,Dashboard!B3+SUM(N$2:N7)) -> 4972
L8: =K8*100*I8 -> 0 | M8: =K8*100*J8 -> 0 | N8: =IF(O8="Win",M8,IF(O8="Loss",-L8,"")) | Q8: =IF(SUM(N$2:N8)="",Dashboard!B3,Dashboard!B3+SUM(N$2:N8)) -> 4972
L9: =K9*100*I9 -> 0 | M9: =K9*100*J9 -> 0 | N9: =IF(O9="Win",M9,IF(O9="Loss",-L9,"")) | Q9: =IF(SUM(N$2:N9)="",Dashboard!B3,Dashboard!B3+SUM(N$2:N9)) -> 4972
L10: =K10*100*I10 -> 0 | M10: =K10*100*J10 -> 0 | N10: =IF(O10="Win",M10,IF(O10="Loss",-L10,"")) | Q10: =IF(SUM(N$2:N10)="",Dashboard!B3,Dashboard!B3+SUM(N$2:N10)) -> 4972
L11: =K11*100*I11 -> 0 | M11: =K11*100*J11 -> 0 | N11: =IF(O11="Win",M11,IF(O11="Loss",-L11,"")) | Q11: =IF(SUM(N$2:N11)="",Dashboard!B3,Dashboard!B3+SUM(N$2:N11)) -> 4972
L12: =K12*100*I12 -> 0 | M12: =K12*100*J12 -> 0 | N12: =IF(O12="Win",M12,IF(O12="Loss",-L12,"")) | Q12: =IF(SUM(N$2:N12)="",Dashboard!B3,Dashboard!B3+SUM(N$2:N12)) -> 4972
L13: =K13*100*I13 -> 0 | M13: =K13*100*J13 -> 0 | N13: =IF(O13="Win",M13,IF(O13="Loss",-L13,"")) | Q13: =IF(SUM(N$2:N13)="",Dashboard!B3,Dashboard!B3+SUM(N$2:N13)) -> 4972
L14: =K14*100*I14 -> 0 | M14: =K14*100*J14 -> 0 | N14: =IF(O14="Win",M14,IF(O14="Loss",-L14,"")) | Q14: =IF(SUM(N$2:N14)="",Dashboard!B3,Dashboard!B3+SUM(N$2:N14)) -> 4972
L15: =K15*100*I15 -> 0 | M15: =K15*100*J15 -> 0 | N15: =IF(O15="Win",M15,IF(O15="Loss",-L15,"")) | Q15: =IF(SUM(N$2:N15)="",Dashboard!B3,Dashboard!B3+SUM(N$2:N15)) -> 4972
L16: =K16*100*I16 -> 0 | M16: =K16*100*J16 -> 0 | N16: =IF(O16="Win",M16,IF(O16="Loss",-L16,"")) | Q16: =IF(SUM(N$2:N16)="",Dashboard!B3,Dashboard!B3+SUM(N$2:N16)) -> 4972
L17: =K17*100*I17 -> 0 | M17: =K17*100*J17 -> 0 | N17: =IF(O17="Win",M17,IF(O17="Loss",-L17,"")) | Q17: =IF(SUM(N$2:N17)="",Dashboard!B3,Dashboard!B3+SUM(N$2:N17)) -> 4972
L18: =K18*100*I18 -> 0 | M18: =K18*100*J18 -> 0 | N18: =IF(O18="Win",M18,IF(O18="Loss",-L18,"")) | Q18: =IF(SUM(N$2:N18)="",Dashboard!B3,Dashboard!B3+SUM(N$2:N18)) -> 4972
L19: =K19*100*I19 -> 0 | M19: =K19*100*J19 -> 0 | N19: =IF(O19="Win",M19,IF(O19="Loss",-L19,"")) | Q19: =IF(SUM(N$2:N19)="",Dashboard!B3,Dashboard!B3+SUM(N$2:N19)) -> 4972
L20: =K20*100*I20 -> 0 | M20: =K20*100*J20 -> 0 | N20: =IF(O20="Win",M20,IF(O20="Loss",-L20,"")) | Q20: =IF(SUM(N$2:N20)="",Dashboard!B3,Dashboard!B3+SUM(N$2:N20)) -> 4972
L21: =K21*100*I21 -> 0 | M21: =K21*100*J21 -> 0 | N21: =IF(O21="Win",M21,IF(O21="Loss",-L21,"")) | Q21: =IF(SUM(N$2:N21)="",Dashboard!B3,Dashboard!B3+SUM(N$2:N21)) -> 4972
L22: =K22*100*I22 -> 0 | M22: =K22*100*J22 -> 0 | N22: =IF(O22="Win",M22,IF(O22="Loss",-L22,"")) | Q22: =IF(SUM(N$2:N22)="",Dashboard!B3,Dashboard!B3+SUM(N$2:N22)) -> 4972
L23: =K23*100*I23 -> 0 | M23: =K23*100*J23 -> 0 | N23: =IF(O23="Win",M23,IF(O23="Loss",-L23,"")) | Q23: =IF(SUM(N$2:N23)="",Dashboard!B3,Dashboard!B3+SUM(N$2:N23)) -> 4972
L24: =K24*100*I24 -> 0 | M24: =K24*100*J24 -> 0 | N24: =IF(O24="Win",M24,IF(O24="Loss",-L24,"")) | Q24: =IF(SUM(N$2:N24)="",Dashboard!B3,Dashboard!B3+SUM(N$2:N24)) -> 4972
L25: =K25*100*I25 -> 0 | M25: =K25*100*J25 -> 0 | N25: =IF(O25="Win",M25,IF(O25="Loss",-L25,"")) | Q25: =IF(SUM(N$2:N25)="",Dashboard!B3,Dashboard!B3+SUM(N$2:N25)) -> 4972
L26: =K26*100*I26 -> 0 | M26: =K26*100*J26 -> 0 | N26: =IF(O26="Win",M26,IF(O26="Loss",-L26,"")) | Q26: =IF(SUM(N$2:N26)="",Dashboard!B3,Dashboard!B3+SUM(N$2:N26)) -> 4972
L27: =K27*100*I27 -> 0 | M27: =K27*100*J27 -> 0 | N27: =IF(O27="Win",M27,IF(O27="Loss",-L27,"")) | Q27: =IF(SUM(N$2:N27)="",Dashboard!B3,Dashboard!B3+SUM(N$2:N27)) -> 4972
L28: =K28*100*I28 -> 0 | M28: =K28*100*J28 -> 0 | N28: =IF(O28="Win",M28,IF(O28="Loss",-L28,"")) | Q28: =IF(SUM(N$2:N28)="",Dashboard!B3,Dashboard!B3+SUM(N$2:N28)) -> 4972
L29: =K29*100*I29 -> 0 | M29: =K29*100*J29 -> 0 | N29: =IF(O29="Win",M29,IF(O29="Loss",-L29,"")) | Q29: =IF(SUM(N$2:N29)="",Dashboard!B3,Dashboard!B3+SUM(N$2:N29)) -> 4972
L30: =K30*100*I30 -> 0 | M30: =K30*100*J30 -> 0 | N30: =IF(O30="Win",M30,IF(O30="Loss",-L30,"")) | Q30: =IF(SUM(N$2:N30)="",Dashboard!B3,Dashboard!B3+SUM(N$2:N30)) -> 4972
L31: =K31*100*I31 -> 0 | M31: =K31*100*J31 -> 0 | N31: =IF(O31="Win",M31,IF(O31="Loss",-L31,"")) | Q31: =IF(SUM(N$2:N31)="",Dashboard!B3,Dashboard!B3+SUM(N$2:N31)) -> 4972
L32: =K32*100*I32 -> 0 | M32: =K32*100*J32 -> 0 | N32: =IF(O32="Win",M32,IF(O32="Loss",-L32,"")) | Q32: =IF(SUM(N$2:N32)="",Dashboard!B3,Dashboard!B3+SUM(N$2:N32)) -> 4972
L33: =K33*100*I33 -> 0 | M33: =K33*100*J33 -> 0 | N33: =IF(O33="Win",M33,IF(O33="Loss",-L33,"")) | Q33: =IF(SUM(N$2:N33)="",Dashboard!B3,Dashboard!B3+SUM(N$2:N33)) -> 4972
L34: =K34*100*I34 -> 0 | M34: =K34*100*J34 -> 0 | N34: =IF(O34="Win",M34,IF(O34="Loss",-L34,"")) | Q34: =IF(SUM(N$2:N34)="",Dashboard!B3,Dashboard!B3+SUM(N$2:N34)) -> 4972
L35: =K35*100*I35 -> 0 | M35: =K35*100*J35 -> 0 | N35: =IF(O35="Win",M35,IF(O35="Loss",-L35,"")) | Q35: =IF(SUM(N$2:N35)="",Dashboard!B3,Dashboard!B3+SUM(N$2:N35)) -> 4972
L36: =K36*100*I36 -> 0 | M36: =K36*100*J36 -> 0 | N36: =IF(O36="Win",M36,IF(O36="Loss",-L36,"")) | Q36: =IF(SUM(N$2:N36)="",Dashboard!B3,Dashboard!B3+SUM(N$2:N36)) -> 4972
L37: =K37*100*I37 -> 0 | M37: =K37*100*J37 -> 0 | N37: =IF(O37="Win",M37,IF(O37="Loss",-L37,"")) | Q37: =IF(SUM(N$2:N37)="",Dashboard!B3,Dashboard!B3+SUM(N$2:N37)) -> 4972
L38: =K38*100*I38 -> 0 | M38: =K38*100*J38 -> 0 | N38: =IF(O38="Win",M38,IF(O38="Loss",-L38,"")) | Q38: =IF(SUM(N$2:N38)="",Dashboard!B3,Dashboard!B3+SUM(N$2:N38)) -> 4972
L39: =K39*100*I39 -> 0 | M39: =K39*100*J39 -> 0 | N39: =IF(O39="Win",M39,IF(O39="Loss",-L39,"")) | Q39: =IF(SUM(N$2:N39)="",Dashboard!B3,Dashboard!B3+SUM(N$2:N39)) -> 4972
L40: =K40*100*I40 -> 0 | M40: =K40*100*J40 -> 0 | N40: =IF(O40="Win",M40,IF(O40="Loss",-L40,"")) | Q40: =IF(SUM(N$2:N40)="",Dashboard!B3,Dashboard!B3+SUM(N$2:N40)) -> 4972
L41: =K41*100*I41 -> 0 | M41: =K41*100*J41 -> 0 | N41: =IF(O41="Win",M41,IF(O41="Loss",-L41,"")) | Q41: =IF(SUM(N$2:N41)="",Dashboard!B3,Dashboard!B3+SUM(N$2:N41)) -> 4972
L42: =K42*100*I42 -> 0 | M42: =K42*100*J42 -> 0 | N42: =IF(O42="Win",M42,IF(O42="Loss",-L42,"")) | Q42: =IF(SUM(N$2:N42)="",Dashboard!B3,Dashboard!B3+SUM(N$2:N42)) -> 4972
L43: =K43*100*I43 -> 0 | M43: =K43*100*J43 -> 0 | N43: =IF(O43="Win",M43,IF(O43="Loss",-L43,"")) | Q43: =IF(SUM(N$2:N43)="",Dashboard!B3,Dashboard!B3+SUM(N$2:N43)) -> 4972
L44: =K44*100*I44 -> 0 | M44: =K44*100*J44 -> 0 | N44: =IF(O44="Win",M44,IF(O44="Loss",-L44,"")) | Q44: =IF(SUM(N$2:N44)="",Dashboard!B3,Dashboard!B3+SUM(N$2:N44)) -> 4972
L45: =K45*100*I45 -> 0 | M45: =K45*100*J45 -> 0 | N45: =IF(O45="Win",M45,IF(O45="Loss",-L45,"")) | Q45: =IF(SUM(N$2:N45)="",Dashboard!B3,Dashboard!B3+SUM(N$2:N45)) -> 4972
L46: =K46*100*I46 -> 0 | M46: =K46*100*J46 -> 0 | N46: =IF(O46="Win",M46,IF(O46="Loss",-L46,"")) | Q46: =IF(SUM(N$2:N46)="",Dashboard!B3,Dashboard!B3+SUM(N$2:N46)) -> 4972
L47: =K47*100*I47 -> 0 | M47: =K47*100*J47 -> 0 | N47: =IF(O47="Win",M47,IF(O47="Loss",-L47,"")) | Q47: =IF(SUM(N$2:N47)="",Dashboard!B3,Dashboard!B3+SUM(N$2:N47)) -> 4972
L48: =K48*100*I48 -> 0 | M48: =K48*100*J48 -> 0 | N48: =IF(O48="Win",M48,IF(O48="Loss",-L48,"")) | Q48: =IF(SUM(N$2:N48)="",Dashboard!B3,Dashboard!B3+SUM(N$2:N48)) -> 4972
L49: =K49*100*I49 -> 0 | M49: =K49*100*J49 -> 0 | N49: =IF(O49="Win",M49,IF(O49="Loss",-L49,"")) | Q49: =IF(SUM(N$2:N49)="",Dashboard!B3,Dashboard!B3+SUM(N$2:N49)) -> 4972
L50: =K50*100*I50 -> 0 | M50: =K50*100*J50 -> 0 | N50: =IF(O50="Win",M50,IF(O50="Loss",-L50,"")) | Q50: =IF(SUM(N$2:N50)="",Dashboard!B3,Dashboard!B3+SUM(N$2:N50)) -> 4972
L51: =K51*100*I51 -> 0 | M51: =K51*100*J51 -> 0 | N51: =IF(O51="Win",M51,IF(O51="Loss",-L51,"")) | Q51: =IF(SUM(N$2:N51)="",Dashboard!B3,Dashboard!B3+SUM(N$2:N51)) -> 4972
L52: =K52*100*I52 -> 0 | M52: =K52*100*J52 -> 0 | N52: =IF(O52="Win",M52,IF(O52="Loss",-L52,"")) | Q52: =IF(SUM(N$2:N52)="",Dashboard!B3,Dashboard!B3+SUM(N$2:N52)) -> 4972
L53: =K53*100*I53 -> 0 | M53: =K53*100*J53 -> 0 | N53: =IF(O53="Win",M53,IF(O53="Loss",-L53,"")) | Q53: =IF(SUM(N$2:N53)="",Dashboard!B3,Dashboard!B3+SUM(N$2:N53)) -> 4972
L54: =K54*100*I54 -> 0 | M54: =K54*100*J54 -> 0 | N54: =IF(O54="Win",M54,IF(O54="Loss",-L54,"")) | Q54: =IF(SUM(N$2:N54)="",Dashboard!B3,Dashboard!B3+SUM(N$2:N54)) -> 4972
L55: =K55*100*I55 -> 0 | M55: =K55*100*J55 -> 0 | N55: =IF(O55="Win",M55,IF(O55="Loss",-L55,"")) | Q55: =IF(SUM(N$2:N55)="",Dashboard!B3,Dashboard!B3+SUM(N$2:N55)) -> 4972
L56: =K56*100*I56 -> 0 | M56: =K56*100*J56 -> 0 | N56: =IF(O56="Win",M56,IF(O56="Loss",-L56,"")) | Q56: =IF(SUM(N$2:N56)="",Dashboard!B3,Dashboard!B3+SUM(N$2:N56)) -> 4972
L57: =K57*100*I57 -> 0 | M57: =K57*100*J57 -> 0 | N57: =IF(O57="Win",M57,IF(O57="Loss",-L57,"")) | Q57: =IF(SUM(N$2:N57)="",Dashboard!B3,Dashboard!B3+SUM(N$2:N57)) -> 4972
L58: =K58*100*I58 -> 0 | M58: =K58*100*J58 -> 0 | N58: =IF(O58="Win",M58,IF(O58="Loss",-L58,"")) | Q58: =IF(SUM(N$2:N58)="",Dashboard!B3,Dashboard!B3+SUM(N$2:N58)) -> 4972
L59: =K59*100*I59 -> 0 | M59: =K59*100*J59 -> 0 | N59: =IF(O59="Win",M59,IF(O59="Loss",-L59,"")) | Q59: =IF(SUM(N$2:N59)="",Dashboard!B3,Dashboard!B3+SUM(N$2:N59)) -> 4972
L60: =K60*100*I60 -> 0 | M60: =K60*100*J60 -> 0 | N60: =IF(O60="Win",M60,IF(O60="Loss",-L60,"")) | Q60: =IF(SUM(N$2:N60)="",Dashboard!B3,Dashboard!B3+SUM(N$2:N60)) -> 4972
L61: =K61*100*I61 -> 0 | M61: =K61*100*J61 -> 0 | N61: =IF(O61="Win",M61,IF(O61="Loss",-L61,"")) | Q61: =IF(SUM(N$2:N61)="",Dashboard!B3,Dashboard!B3+SUM(N$2:N61)) -> 4972
L62: =K62*100*I62 -> 0 | M62: =K62*100*J62 -> 0 | N62: =IF(O62="Win",M62,IF(O62="Loss",-L62,"")) | Q62: =IF(SUM(N$2:N62)="",Dashboard!B3,Dashboard!B3+SUM(N$2:N62)) -> 4972
L63: =K63*100*I63 -> 0 | M63: =K63*100*J63 -> 0 | N63: =IF(O63="Win",M63,IF(O63="Loss",-L63,"")) | Q63: =IF(SUM(N$2:N63)="",Dashboard!B3,Dashboard!B3+SUM(N$2:N63)) -> 4972
L64: =K64*100*I64 -> 0 | M64: =K64*100*J64 -> 0 | N64: =IF(O64="Win",M64,IF(O64="Loss",-L64,"")) | Q64: =IF(SUM(N$2:N64)="",Dashboard!B3,Dashboard!B3+SUM(N$2:N64)) -> 4972
L65: =K65*100*I65 -> 0 | M65: =K65*100*J65 -> 0 | N65: =IF(O65="Win",M65,IF(O65="Loss",-L65,"")) | Q65: =IF(SUM(N$2:N65)="",Dashboard!B3,Dashboard!B3+SUM(N$2:N65)) -> 4972
L66: =K66*100*I66 -> 0 | M66: =K66*100*J66 -> 0 | N66: =IF(O66="Win",M66,IF(O66="Loss",-L66,"")) | Q66: =IF(SUM(N$2:N66)="",Dashboard!B3,Dashboard!B3+SUM(N$2:N66)) -> 4972
L67: =K67*100*I67 -> 0 | M67: =K67*100*J67 -> 0 | N67: =IF(O67="Win",M67,IF(O67="Loss",-L67,"")) | Q67: =IF(SUM(N$2:N67)="",Dashboard!B3,Dashboard!B3+SUM(N$2:N67)) -> 4972
L68: =K68*100*I68 -> 0 | M68: =K68*100*J68 -> 0 | N68: =IF(O68="Win",M68,IF(O68="Loss",-L68,"")) | Q68: =IF(SUM(N$2:N68)="",Dashboard!B3,Dashboard!B3+SUM(N$2:N68)) -> 4972
L69: =K69*100*I69 -> 0 | M69: =K69*100*J69 -> 0 | N69: =IF(O69="Win",M69,IF(O69="Loss",-L69,"")) | Q69: =IF(SUM(N$2:N69)="",Dashboard!B3,Dashboard!B3+SUM(N$2:N69)) -> 4972
L70: =K70*100*I70 -> 0 | M70: =K70*100*J70 -> 0 | N70: =IF(O70="Win",M70,IF(O70="Loss",-L70,"")) | Q70: =IF(SUM(N$2:N70)="",Dashboard!B3,Dashboard!B3+SUM(N$2:N70)) -> 4972
L71: =K71*100*I71 -> 0 | M71: =K71*100*J71 -> 0 | N71: =IF(O71="Win",M71,IF(O71="Loss",-L71,"")) | Q71: =IF(SUM(N$2:N71)="",Dashboard!B3,Dashboard!B3+SUM(N$2:N71)) -> 4972
L72: =K72*100*I72 -> 0 | M72: =K72*100*J72 -> 0 | N72: =IF(O72="Win",M72,IF(O72="Loss",-L72,"")) | Q72: =IF(SUM(N$2:N72)="",Dashboard!B3,Dashboard!B3+SUM(N$2:N72)) -> 4972
L73: =K73*100*I73 -> 0 | M73: =K73*100*J73 -> 0 | N73: =IF(O73="Win",M73,IF(O73="Loss",-L73,"")) | Q73: =IF(SUM(N$2:N73)="",Dashboard!B3,Dashboard!B3+SUM(N$2:N73)) -> 4972
L74: =K74*100*I74 -> 0 | M74: =K74*100*J74 -> 0 | N74: =IF(O74="Win",M74,IF(O74="Loss",-L74,"")) | Q74: =IF(SUM(N$2:N74)="",Dashboard!B3,Dashboard!B3+SUM(N$2:N74)) -> 4972
L75: =K75*100*I75 -> 0 | M75: =K75*100*J75 -> 0 | N75: =IF(O75="Win",M75,IF(O75="Loss",-L75,"")) | Q75: =IF(SUM(N$2:N75)="",Dashboard!B3,Dashboard!B3+SUM(N$2:N75)) -> 4972
L76: =K76*100*I76 -> 0 | M76: =K76*100*J76 -> 0 | N76: =IF(O76="Win",M76,IF(O76="Loss",-L76,"")) | Q76: =IF(SUM(N$2:N76)="",Dashboard!B3,Dashboard!B3+SUM(N$2:N76)) -> 4972
L77: =K77*100*I77 -> 0 | M77: =K77*100*J77 -> 0 | N77: =IF(O77="Win",M77,IF(O77="Loss",-L77,"")) | Q77: =IF(SUM(N$2:N77)="",Dashboard!B3,Dashboard!B3+SUM(N$2:N77)) -> 4972
L78: =K78*100*I78 -> 0 | M78: =K78*100*J78 -> 0 | N78: =IF(O78="Win",M78,IF(O78="Loss",-L78,"")) | Q78: =IF(SUM(N$2:N78)="",Dashboard!B3,Dashboard!B3+SUM(N$2:N78)) -> 4972
L79: =K79*100*I79 -> 0 | M79: =K79*100*J79 -> 0 | N79: =IF(O79="Win",M79,IF(O79="Loss",-L79,"")) | Q79: =IF(SUM(N$2:N79)="",Dashboard!B3,Dashboard!B3+SUM(N$2:N79)) -> 4972
L80: =K80*100*I80 -> 0 | M80: =K80*100*J80 -> 0 | N80: =IF(O80="Win",M80,IF(O80="Loss",-L80,"")) | Q80: =IF(SUM(N$2:N80)="",Dashboard!B3,Dashboard!B3+SUM(N$2:N80)) -> 4972
L81: =K81*100*I81 -> 0 | M81: =K81*100*J81 -> 0 | N81: =IF(O81="Win",M81,IF(O81="Loss",-L81,"")) | Q81: =IF(SUM(N$2:N81)="",Dashboard!B3,Dashboard!B3+SUM(N$2:N81)) -> 4972
L82: =K82*100*I82 -> 0 | M82: =K82*100*J82 -> 0 | N82: =IF(O82="Win",M82,IF(O82="Loss",-L82,"")) | Q82: =IF(SUM(N$2:N82)="",Dashboard!B3,Dashboard!B3+SUM(N$2:N82)) -> 4972
L83: =K83*100*I83 -> 0 | M83: =K83*100*J83 -> 0 | N83: =IF(O83="Win",M83,IF(O83="Loss",-L83,"")) | Q83: =IF(SUM(N$2:N83)="",Dashboard!B3,Dashboard!B3+SUM(N$2:N83)) -> 4972
L84: =K84*100*I84 -> 0 | M84: =K84*100*J84 -> 0 | N84: =IF(O84="Win",M84,IF(O84="Loss",-L84,"")) | Q84: =IF(SUM(N$2:N84)="",Dashboard!B3,Dashboard!B3+SUM(N$2:N84)) -> 4972
L85: =K85*100*I85 -> 0 | M85: =K85*100*J85 -> 0 | N85: =IF(O85="Win",M85,IF(O85="Loss",-L85,"")) | Q85: =IF(SUM(N$2:N85)="",Dashboard!B3,Dashboard!B3+SUM(N$2:N85)) -> 4972
L86: =K86*100*I86 -> 0 | M86: =K86*100*J86 -> 0 | N86: =IF(O86="Win",M86,IF(O86="Loss",-L86,"")) | Q86: =IF(SUM(N$2:N86)="",Dashboard!B3,Dashboard!B3+SUM(N$2:N86)) -> 4972
L87: =K87*100*I87 -> 0 | M87: =K87*100*J87 -> 0 | N87: =IF(O87="Win",M87,IF(O87="Loss",-L87,"")) | Q87: =IF(SUM(N$2:N87)="",Dashboard!B3,Dashboard!B3+SUM(N$2:N87)) -> 4972
L88: =K88*100*I88 -> 0 | M88: =K88*100*J88 -> 0 | N88: =IF(O88="Win",M88,IF(O88="Loss",-L88,"")) | Q88: =IF(SUM(N$2:N88)="",Dashboard!B3,Dashboard!B3+SUM(N$2:N88)) -> 4972
L89: =K89*100*I89 -> 0 | M89: =K89*100*J89 -> 0 | N89: =IF(O89="Win",M89,IF(O89="Loss",-L89,"")) | Q89: =IF(SUM(N$2:N89)="",Dashboard!B3,Dashboard!B3+SUM(N$2:N89)) -> 4972
L90: =K90*100*I90 -> 0 | M90: =K90*100*J90 -> 0 | N90: =IF(O90="Win",M90,IF(O90="Loss",-L90,"")) | Q90: =IF(SUM(N$2:N90)="",Dashboard!B3,Dashboard!B3+SUM(N$2:N90)) -> 4972
L91: =K91*100*I91 -> 0 | M91: =K91*100*J91 -> 0 | N91: =IF(O91="Win",M91,IF(O91="Loss",-L91,"")) | Q91: =IF(SUM(N$2:N91)="",Dashboard!B3,Dashboard!B3+SUM(N$2:N91)) -> 4972
L92: =K92*100*I92 -> 0 | M92: =K92*100*J92 -> 0 | N92: =IF(O92="Win",M92,IF(O92="Loss",-L92,"")) | Q92: =IF(SUM(N$2:N92)="",Dashboard!B3,Dashboard!B3+SUM(N$2:N92)) -> 4972
L93: =K93*100*I93 -> 0 | M93: =K93*100*J93 -> 0 | N93: =IF(O93="Win",M93,IF(O93="Loss",-L93,"")) | Q93: =IF(SUM(N$2:N93)="",Dashboard!B3,Dashboard!B3+SUM(N$2:N93)) -> 4972
L94: =K94*100*I94 -> 0 | M94: =K94*100*J94 -> 0 | N94: =IF(O94="Win",M94,IF(O94="Loss",-L94,"")) | Q94: =IF(SUM(N$2:N94)="",Dashboard!B3,Dashboard!B3+SUM(N$2:N94)) -> 4972
L95: =K95*100*I95 -> 0 | M95: =K95*100*J95 -> 0 | N95: =IF(O95="Win",M95,IF(O95="Loss",-L95,"")) | Q95: =IF(SUM(N$2:N95)="",Dashboard!B3,Dashboard!B3+SUM(N$2:N95)) -> 4972
L96: =K96*100*I96 -> 0 | M96: =K96*100*J96 -> 0 | N96: =IF(O96="Win",M96,IF(O96="Loss",-L96,"")) | Q96: =IF(SUM(N$2:N96)="",Dashboard!B3,Dashboard!B3+SUM(N$2:N96)) -> 4972
L97: =K97*100*I97 -> 0 | M97: =K97*100*J97 -> 0 | N97: =IF(O97="Win",M97,IF(O97="Loss",-L97,"")) | Q97: =IF(SUM(N$2:N97)="",Dashboard!B3,Dashboard!B3+SUM(N$2:N97)) -> 4972
L98: =K98*100*I98 -> 0 | M98: =K98*100*J98 -> 0 | N98: =IF(O98="Win",M98,IF(O98="Loss",-L98,"")) | Q98: =IF(SUM(N$2:N98)="",Dashboard!B3,Dashboard!B3+SUM(N$2:N98)) -> 4972
L99: =K99*100*I99 -> 0 | M99: =K99*100*J99 -> 0 | N99: =IF(O99="Win",M99,IF(O99="Loss",-L99,"")) | Q99: =IF(SUM(N$2:N99)="",Dashboard!B3,Dashboard!B3+SUM(N$2:N99)) -> 4972
L100: =K100*100*I100 -> 0 | M100: =K100*100*J100 -> 0 | N100: =IF(O100="Win",M100,IF(O100="Loss",-L100,"")) | Q100: =IF(SUM(N$2:N100)="",Dashboard!B3,Dashboard!B3+SUM(N$2:N100)) -> 4972
...

Sheet Stats
A1: Total Trades | B1: =COUNTA(Trade_Journal!A2:A500) -> 3
A2: Winning Trades | B2: =COUNTIF(Trade_Journal!O2:O500,"Win") -> 2
A3: Losing Trades | B3: =COUNTIF(Trade_Journal!O2:O500,"Loss") -> 1
A4: Win Rate % | B4: =IF(B1=0,0,B2/B1) -> 0.66666667
A6: Total P/L ($) | B6: =SUM(Trade_Journal!N2:N500) -> -28
A7: Current Equity ($) | B7: =Dashboard!B3 + B6 -> 4972
A8: Peak Equity ($) | B8: =MAX(Trade_Journal!Q2:Q500) -> 5010
A9: Max Drawdown ($) | B9: =B8 - B7 -> 38
A10: Max Drawdown % | B10: =IF(B8=0,0,B9/B8) -> 0.0075848303

Sheet Progress
A1: Phase 1 Target (10%) | B1: =Dashboard!B7 -> 500
A2: Phase 2 Target (5%) | B2: =Dashboard!B8 -> 250
A4: Current Realized P/L ($) | B4: =Stats!B6 -> -28
A5: Progress to Phase1 (%) | B5: =MIN(1,IF(B4<=0,0,B4/B1)) -> 0
A6: Progress to Phase2 (%) | B6: =MIN(1,IF(B4<=0,0,B4/B2)) -> 0

Sheet READ ME
A1: ⚠️ READ ME FIRST – HOW TO USE THIS TRADING JOURNAL
A3: EDIT ONLY THESE COLUMNS IN Trade_Journal:
A4: Date, Session, Pair, Setup Type, Direction, Entry, SL, TP, SL pips, TP pips, Lot, Outcome, Rule Followed, Notes
A6: DO NOT EDIT:
A7: Risk $, Reward $, Result $, Equity After Trade, Stats sheet, Progress sheet
A9: HOW IT WORKS:
A10: • Risk $ = Lot × 100 × SL pips
A11: • Reward $ = Lot × 100 × TP pips
A12: • Result $ auto-calculates based on Win/Loss
A13: • Progress updates automatically toward 10% and 5% targets
A15: COLOR GUIDE:
A16: Green = Profit, Red = Loss, Yellow = Rule Broken
... A21: 3. Review Stats & Progress

Sheet 1-PAGE GUIDE
A1: XAUUSD TRADING JOURNAL – QUICK GUIDE
A3: PAIR: XAUUSD | SL: 12 pips | TP: 5 pips
A4: ACCOUNT: $10,000 | TARGET: 10% then 5%
A6: ENTER DATA ONLY IN Trade_Journal
A7: ONE ROW = ONE TRADE
A9: GREEN = WIN | RED = LOSS | YELLOW = RULE BROKEN
A11: NEVER EDIT FORMULA CELLS
A13: CHECK Stats & Progress DAILY
